detectaicore/__init__.py
detectaicore/classes/__init__.py
detectaicore/classes/datadetectclasses.py
detectaicore/src/__init__.py
detectaicore/src/constants.py
detectaicore/src/constants_pii.py
detectaicore/src/environment.py
detectaicore/src/logger_util.py
detectaicore/src/nats_utils.py
detectaicore/src/schemas.py
detectaicore/src/ssl_utils.py
detectaicore/src/utils.py
detectaicore-0.0.29.dist-info/METADATA
detectaicore-0.0.29.dist-info/WHEEL
detectaicore-0.0.29.dist-info/top_level.txt
detectaicore-0.0.29.dist-info/RECORD
