Metadata-Version: 2.1
Name: detectaicore
Version: 0.0.29
Summary: Detect-ai core package
Author: Juan Huertas
Author-email: 
Keywords: python,core package
Classifier: Intended Audience :: Other Audience
Classifier: Programming Language :: Python :: 3
Classifier: Operating System :: POSIX :: Linux
